{
    "display": {
        "icon": {
            "item": "minecraft:player_head",
			"nbt": "{\"SkullOwner\":\"Madnstar\"}"
        },
        "title": {"translate":"Sopita Maruchan"},
        "description": {"translate":"Sobreviviste más tiempo que Madnstar en la Temporada 1"},
		"hidden": true
    },
	"parent":"uhc:cpt_armenia",
    "criteria": {
        "minecraft:bedrock": {
            "trigger": "minecraft:inventory_changed",
            "conditions": {
                "items": [
                    {
                        "item": "minecraft:bedrock"
                    }
                ]
            }
        }
    }
}